zne/__init__.py
zne/immutable_strategy.py
zne/types.py
zne/zne_strategy.py
zne/extrapolation/__init__.py
zne/extrapolation/exponential_extrapolator.py
zne/extrapolation/extrapolator.py
zne/extrapolation/polynomial_extrapolator.py
zne/meta/__init__.py
zne/meta/call.py
zne/meta/cls.py
zne/meta/init.py
zne/meta/job.py
zne/meta/run.py
zne/noise_amplification/__init__.py
zne/noise_amplification/noise_amplifier.py
zne/noise_amplification/folding_amplifier/__init__.py
zne/noise_amplification/folding_amplifier/folding_amplifier.py
zne/noise_amplification/folding_amplifier/global_folding_amplifier.py
zne/noise_amplification/folding_amplifier/local_folding_amplifier.py
zne/qiskit/__init__.py
zne/qiskit/primitives/__init__.py
zne/utils/__init__.py
zne/utils/classconstant.py
zne/utils/docstrings.py
zne/utils/grouping.py
zne/utils/serialization.py
zne/utils/standard_gates.py
zne/utils/strategy.py
zne/utils/typing.py
zne/utils/unset.py
zne/utils/validation.py
prototype_zne-1.3.1.dist-info/LICENSE.txt
prototype_zne-1.3.1.dist-info/WHEEL
prototype_zne-1.3.1.dist-info/METADATA
prototype_zne-1.3.1.dist-info/RECORD
