Metadata-Version: 2.1
Name: prototype-zne
Version: 1.3.1
Summary: Zero Noise Extrapolation (ZNE) prototype for error mitigation on
Keywords: error mitigation,zero noise extrapolation,quantum computing,quantum information science,qiskit
Author: Friederike Metz, Areeq Hasan
Author-email: Pedro Rivero <pedro.rivero@ibm.com>, Caleb Johnson <caleb.johnson@ibm.com>, Agata Branczyk <agata.branczyk@ibm.com>
Maintainer-email: Pedro Rivero <pedro.rivero@ibm.com>
Requires-Python: >=3.8
Classifier: Development Status :: 5 - Production/Stable
Classifier: Intended Audience :: Developers
Classifier: Intended Audience :: Education
Classifier: Intended Audience :: Science/Research
Classifier: License :: OSI Approved :: Apache Software License
Classifier: Natural Language :: English
Classifier: Operating System :: MacOS
Classifier: Operating System :: POSIX :: Linux
Classifier: Operating System :: Microsoft :: Windows
Classifier: Programming Language :: Python :: 3.8
Classifier: Programming Language :: Python :: 3.9
Classifier: Programming Language :: Python :: 3.10
Classifier: Programming Language :: Python :: 3.11
Classifier: Programming Language :: Python :: 3.12
Classifier: Topic :: Scientific/Engineering :: Physics
Requires-Dist: qiskit >= 0.45.1
Requires-Dist: tox >= 4.4.6 ; extra == "dev"
Requires-Dist: pre-commit >= 2.19.0 ; extra == "dev"
Requires-Dist: commitizen >= 2.28.0 ; extra == "dev"
Requires-Dist: jupyter-sphinx >= 0.3.2 ; extra == "docs"
Requires-Dist: nbsphinx >= 0.8.8 ; extra == "docs"
Requires-Dist: reno >= 3.5.0 ; extra == "docs"
Requires-Dist: sphinx-autodoc-typehints >= 1.17.0 ; extra == "docs"
Requires-Dist: autoflake >= 1.7.6 ; extra == "lint"
Requires-Dist: black[jupyter] ~= 22.6.0 ; extra == "lint"
Requires-Dist: flake8 >= 4.0.1 ; extra == "lint"
Requires-Dist: isort >= 5.10.1 ; extra == "lint"
Requires-Dist: mypy >= 0.961 ; extra == "lint"
Requires-Dist: mypy-extensions >= 0.4.3 ; extra == "lint"
Requires-Dist: pylint >= 2.14.4 ; extra == "lint"
Requires-Dist: jupyter >= 1.0.0 ; extra == "notebook"
Requires-Dist: notebook >= 6.4.12 ; extra == "notebook"
Requires-Dist: qiskit[visualization] >= 0.45.1 ; extra == "notebook"
Requires-Dist: qiskit-aer >= 0.13.1 ; extra == "notebook"
Requires-Dist: nbqa >= 1.3.1 ; extra == "notebook"
Requires-Dist: treon >= 0.1.3 ; extra == "notebook"
Requires-Dist: pytest >= 7.1.2 ; extra == "test"
Requires-Dist: pytest-cov >= 3.0.0 ; extra == "test"
Requires-Dist: pytest-randomly >= 3.12.0 ; extra == "test"
Requires-Dist: qiskit-aer >= 0.13.1 ; extra == "test"
Project-URL: Documentation, https://github.com/qiskit-community/prototype-zne/tree/main/docs/
Project-URL: Download, https://pypi.org/project/prototype-zne/
Project-URL: Home, https://qiskit-community.github.io/prototypes/
Project-URL: Repository, https://github.com/qiskit-community/prototype-zne/
Provides-Extra: dev
Provides-Extra: docs
Provides-Extra: lint
Provides-Extra: notebook
Provides-Extra: test
